wanabi/app_name.py
wanabi/aqua.py
wanabi/archive.py
wanabi/const.py
wanabi/encoding.py
wanabi/extend_exception.py
wanabi/full_mode.py
wanabi/indent_insert.py
wanabi/independent_method.py
wanabi/lang.py
wanabi/menu_init.py
wanabi/string_decorate.py
wanabi/textarea_config.py
wanabi/theme_mod.py
wanabi/version.py
wanabi/vinegar.py
wanabi/inmemory_module/ram_memo.py
wanabi/keybind/keybind.py
wanabi/log_recorder_me/record_hist.py
wanabi-1.5.3.dist-info/METADATA
wanabi-1.5.3.dist-info/WHEEL
wanabi-1.5.3.dist-info/entry_points.txt
wanabi-1.5.3.dist-info/top_level.txt
wanabi-1.5.3.dist-info/RECORD
