Metadata-Version: 2.4
Name: wanabi
Version: 1.5.3
Summary: a light authoring tool
Author: hiro
Author-email: skylake.author@gmail.com
License-Expression: GPL-3.0-or-later
Classifier: Programming Language :: Python :: 3
Classifier: Operating System :: OS Independent
Requires-Python: >=3.10
Requires-Dist: build
Requires-Dist: twine
Requires-Dist: setuptools
